mathemagic/__init__.py
mathemagic/cli.py
mathemagic/mathemagic.py
mathemagic/server.py
mathemagic_ai-0.1.0.dist-info/METADATA
mathemagic_ai-0.1.0.dist-info/WHEEL
mathemagic_ai-0.1.0.dist-info/entry_points.txt
mathemagic_ai-0.1.0.dist-info/top_level.txt
mathemagic_ai-0.1.0.dist-info/RECORD
