Metadata-Version: 2.4
Name: mathemagic-ai
Version: 0.1.0
Summary: AI Calculator Agent
Requires-Python: >=3.10
Requires-Dist: anthropic>=0.49.0
Requires-Dist: asyncio>=3.4.3
Requires-Dist: fastmcp>=0.4.1
Requires-Dist: mcp[cli]>=1.5.0
Requires-Dist: pint>=0.24.4
Requires-Dist: pylint>=3.3.6
Requires-Dist: pytest>=8.3.5
Requires-Dist: python-dotenv>=1.1.0
Requires-Dist: typer>=0.15.2
